o2_cloudstaff_json2pandas.py
o2_cloudstaff_json2pandas-2.2.dist-info/METADATA
o2_cloudstaff_json2pandas-2.2.dist-info/WHEEL
o2_cloudstaff_json2pandas-2.2.dist-info/top_level.txt
o2_cloudstaff_json2pandas-2.2.dist-info/RECORD
