Metadata-Version: 2.1
Name: o2-cloudstaff-json2pandas
Version: 2.2
Summary: UNKNOWN
Home-page: UNKNOWN
Author: Hudge
Author-email: 
License: UNKNOWN
Platform: UNKNOWN
Classifier: Programming Language :: Python :: 3
Classifier: License :: OSI Approved :: MIT License
Classifier: Operating System :: OS Independent
Requires-Dist: o2-docparser
Requires-Dist: pandas
Requires-Dist: openpyxl
Requires-Dist: money2float
Requires-Dist: o2-google-spreadsheet
